trex/__init__.py
trex/main.py
trex/meta.py
trex/utils.py
trex-0.1.7.dist-info/LICENSE
trex-0.1.7.dist-info/METADATA
trex-0.1.7.dist-info/WHEEL
trex-0.1.7.dist-info/entry_points.txt
trex-0.1.7.dist-info/RECORD
