Metadata-Version: 2.1
Name: trex
Version: 0.1.7
Summary: Templatosaurus Rex 🦖 Create and manage project templates in your terminal
Home-page: https://berrysauce.me/trex
License: GPL-3.0-only
Author: Paul Haedrich
Author-email: paul@berrysauce.me
Requires-Python: >=3.9,<4.0
Classifier: License :: OSI Approved :: GNU General Public License v3 (GPLv3)
Classifier: Programming Language :: Python :: 3
Classifier: Programming Language :: Python :: 3.9
Classifier: Programming Language :: Python :: 3.10
Classifier: Programming Language :: Python :: 3.11
Classifier: Programming Language :: Python :: 3 :: Only
Classifier: Topic :: Software Development
Classifier: Topic :: Software Development :: Version Control :: Git
Classifier: Topic :: Utilities
Requires-Dist: GitPython (>=3.1.27,<4.0.0)
Requires-Dist: requests (>=2.28.1,<3.0.0)
Requires-Dist: tabulate (>=0.8.9,<0.9.0)
Requires-Dist: typer (>=0.4.1,<0.5.0)
Project-URL: Documentation, https://berrysauce.me/trex
Project-URL: Repository, https://github.com/berrysauce/trex
